Metadata-Version: 2.1
Name: blackfriday
Version: 1.0.3
Summary: Black Friday
Home-page: https://realpython.com/blackfriday
Author: Real Python
Author-email: info@realpython.com
License: MIT
Platform: UNKNOWN
Classifier: License :: OSI Approved :: MIT License
Classifier: Programming Language :: Python
Classifier: Programming Language :: Python :: 2
Classifier: Programming Language :: Python :: 3
